tarball_httpd/__init__.py
tarball_httpd/__main__.py
tarball_httpd-0.0.3.dist-info/LICENSE
tarball_httpd-0.0.3.dist-info/METADATA
tarball_httpd-0.0.3.dist-info/WHEEL
tarball_httpd-0.0.3.dist-info/top_level.txt
tarball_httpd-0.0.3.dist-info/RECORD
