Metadata-Version: 2.1
Name: tarball-httpd
Version: 0.0.3
Summary: Simple http server, streaming directories as tarballs.
Home-page: https://github.com/zrthstr/tarball_httpd
Author: zrthstr
Author-email: zrth1k@gmail.com
License: PSFL
Keywords: web http server tarball archive download filesharing stream
Platform: UNKNOWN
Classifier: Programming Language :: Python :: 3
Classifier: License :: OSI Approved :: Python Software Foundation License
Classifier: Topic :: Internet :: WWW/HTTP :: HTTP Servers
Classifier: Topic :: System :: Archiving
Classifier: Topic :: Utilities
Classifier: Topic :: Communications :: File Sharing
Classifier: Operating System :: OS Independent
